Metadata-Version: 1.1
Name: indexed-png-stats
Version: 0.0.4
Summary: Python library that inspects (and can remaps) indexed PNG files.
Home-page: https://github.com/waikato-datamining/indexed-png-stats
Author: Peter Reutemann
Author-email: fracpete@waikato.ac.nz
License: MIT
Platform: UNKNOWN
Classifier: Development Status :: 4 - Beta
Classifier: License :: OSI Approved :: MIT License
Classifier: Topic :: Scientific/Engineering
Classifier: Programming Language :: Python :: 3
